{
  "formatVersion": "2",
  "header": {
    "description": "Equipment Excel Upload SAP Fiori application.",
    "originalLanguage": "en",
    "abapLanguageVersion": "cloudDevelopment"
  },
  "generalInformation": {
    "appType": "ui5",
    "catalogId": "SAP_TC_UI5_REPO_UIAD",
    "targetMappingTitle": "Equipment Mass Replacement Cockpit"
  },
  "ui5AppDetails": {
    "appId": "zpmexceluploadcockpit.hml"
  },
  "navigation": {
    "targetMappingId": "UI5R_31E90F683C711727D7E07CF7619734D1C3F605FC_TM",
    "semanticObject": "zpmexceluploadcockpit",
    "action": "maintain",
    "desktop": true,
    "tablet": true,
    "phone": true
  },
  "tiles": [
    {
      "id": "UI5R_31E90F683C711727D7E07CF7619734D1C3F605FC_AL",
      "tileType": "static",
      "isDefault": true,
      "standard": {
        "title": "Equipment Mass Replacement Cockpit"
      }
    }
  ]
}
